{"appleSKU":"","appleTeamID":"","enableCodelessAutoInitialization":true,"enableUnityGamingServicesAutoInitialization":true,"products":[{"id":"com.defaultcompany.iapandflyweightseherqrupu.500coins","type":0,"storeIDs":[],"defaultDescription":{"googleLocale":4,"title":"500 coins","description":"500 coins for 50% discount"},"screenshotPath":"","applePriceTier":10,"googlePrice":{"data":[999,0,0,131072],"num":9.99},"pricingTemplateID":"","descriptions":[],"udpPrice":{"data":[0,0,0,0],"num":0.0},"payouts":[]},{"id":"com.defaultcompany.iapandflyweightseherqrupu.noads","type":1,"storeIDs":[],"defaultDescription":{"googleLocale":4,"title":"No ads","description":"No ads for 50% discount"},"screenshotPath":"","applePriceTier":6,"googlePrice":{"data":[5,0,0,0],"num":5.0},"pricingTemplateID":"","descriptions":[],"udpPrice":{"data":[0,0,0,0],"num":0.0},"payouts":[]}]}